biocgenerics/__init__.py
biocgenerics/colnames.py
biocgenerics/combine.py
biocgenerics/combine_cols.py
biocgenerics/combine_rows.py
biocgenerics/combine_seqs.py
biocgenerics/rownames.py
biocgenerics/show_as_cell.py
biocgenerics/utils.py
BiocGenerics-0.1.3.dist-info/LICENSE.txt
BiocGenerics-0.1.3.dist-info/METADATA
BiocGenerics-0.1.3.dist-info/WHEEL
BiocGenerics-0.1.3.dist-info/top_level.txt
BiocGenerics-0.1.3.dist-info/RECORD
