Metadata-Version: 2.1
Name: BiocGenerics
Version: 0.1.3
Summary: Generics for core data structures in biocpy
Home-page: https://github.com/biocpy/generics
Author: jkanche
Author-email: jayaram.kancherla@gmail.com
License: MIT
Project-URL: Documentation, https://github.com/biocpy/generics
Platform: any
Classifier: Development Status :: 4 - Beta
Classifier: Programming Language :: Python
Requires-Python: >=3.8
License-File: LICENSE.txt
Requires-Dist: numpy
Requires-Dist: biocutils >=0.0.4
Requires-Dist: importlib-metadata ; python_version < "3.8"
Provides-Extra: optional
Requires-Dist: scipy ; extra == 'optional'
Requires-Dist: pandas ; extra == 'optional'
Provides-Extra: testing
Requires-Dist: setuptools ; extra == 'testing'
Requires-Dist: pytest ; extra == 'testing'
Requires-Dist: pytest-cov ; extra == 'testing'
Requires-Dist: scipy ; extra == 'testing'
Requires-Dist: numpy ; extra == 'testing'
Requires-Dist: pandas ; extra == 'testing'
